surfgram_cli/__init__.py
surfgram_cli/__main__.py
surfgram_cli/cli.py
surfgram_cli/config/__init__.py
surfgram_cli/enums/__init__.py
surfgram_cli/error_handler/__init__.py
surfgram_cli/manager/__init__.py
surfgram_cli/templates/bot_structure/.env.j2
surfgram_cli/templates/bot_structure/__init__.py.j2
surfgram_cli/templates/bot_structure/callback_queries/__init__.py.j2
surfgram_cli/templates/bot_structure/callback_queries/on_button_pressed.py.j2
surfgram_cli/templates/bot_structure/commands/__init__.py.j2
surfgram_cli/templates/bot_structure/commands/help_cmd.py.j2
surfgram_cli/templates/bot_structure/commands/start_cmd.py.j2
surfgram_cli/templates/bot_structure/configs/__init__.py.j2
surfgram_cli/templates/bot_structure/configs/config.py.j2
surfgram_cli/templates/bot_structure/keyboards/__init__.py.j2
surfgram_cli/templates/bot_structure/keyboards/press_me_keyboard.py.j2
surfgram_cli/ui_components/__init__.py
surfgram_cli/ui_components/banner.py
surfgram_cli/ui_components/console.py
surfgram_cli/utils/__init__.py
surfgram_cli/utils/debug.py
surfgram_cli/utils/reloader.py
surfgram_cli-1.2.1.dist-info/entry_points.txt
surfgram_cli-1.2.1.dist-info/LICENSE
surfgram_cli-1.2.1.dist-info/METADATA
surfgram_cli-1.2.1.dist-info/WHEEL
surfgram_cli-1.2.1.dist-info/RECORD
