Metadata-Version: 2.3
Name: surfgram-cli
Version: 1.2.1
Summary: CLI tool for Surfgram Telegram bot framework
License: MIT
Keywords: telegram,bot,cli,terminal,typer,rich,automation,devtools
Author: anybody
Author-email: help.surfgram@email.com
Requires-Python: >=3.9,<4.0
Classifier: Development Status :: 5 - Production/Stable
Classifier: Environment :: Console
Classifier: Intended Audience :: Developers
Classifier: License :: OSI Approved :: MIT License
Classifier: Programming Language :: Python :: 3
Classifier: Programming Language :: Python :: 3.9
Classifier: Programming Language :: Python :: 3.10
Classifier: Programming Language :: Python :: 3.11
Classifier: Programming Language :: Python :: 3.12
Classifier: Programming Language :: Python :: 3.13
Classifier: Topic :: Communications :: Chat
Classifier: Topic :: Software Development :: Libraries :: Application Frameworks
Classifier: Typing :: Typed
Requires-Dist: dotenv (==0.9.9)
Requires-Dist: jinja2 (==3.1.6)
Requires-Dist: pyfiglet (==1.0.2)
Requires-Dist: rich (>=13.7.0,<14.0.0)
Requires-Dist: typer[all] (==0.16.0)
Requires-Dist: watchdog (>=2.1.6,<3.0.0)
Project-URL: Bug Tracker, https://github.com/surfgram/surfgram-cli/issues
Project-URL: Changelog, https://github.com/surfgram/surfgram-cli/releases
Project-URL: Homepage, https://github.com/surfgram/surfgram
Project-URL: Repository, https://github.com/surfgram/surfgram-cli
